llama_models/__init__.py
llama_models/checkpoint.py
llama_models/datatypes.py
llama_models/quantize_impls.py
llama_models/sku_list.py
llama_models/sku_types.py
llama_models/tokenizer_utils.py
llama_models/cli/__init__.py
llama_models/cli/describe.py
llama_models/cli/download.py
llama_models/cli/list.py
llama_models/cli/llama.py
llama_models/cli/prompt_format.py
llama_models/cli/remove.py
llama_models/cli/safety_models.py
llama_models/cli/subcommand.py
llama_models/cli/table.py
llama_models/cli/utils.py
llama_models/cli/verify_download.py
llama_models/llama3/__init__.py
llama_models/llama3/args.py
llama_models/llama3/chat_format.py
llama_models/llama3/generation.py
llama_models/llama3/model.py
llama_models/llama3/tokenizer.model
llama_models/llama3/tokenizer.py
llama_models/llama3/tool_utils.py
llama_models/llama3/multimodal/__init__.py
llama_models/llama3/multimodal/encoder_utils.py
llama_models/llama3/multimodal/image_transform.py
llama_models/llama3/multimodal/model.py
llama_models/llama3/multimodal/utils.py
llama_models/llama3/quantization/loader.py
llama_models/llama3/scripts/__init__.py
llama_models/llama3/scripts/chat_completion.py
llama_models/llama3/scripts/completion.py
llama_models/llama3/tests/api/test_generation.py
llama_models/llama3/tests/api/test_tokenizer.py
llama_models/llama3/tests/api/test_tool_utils.py
llama_models/llama3_1/prompt_format.md
llama_models/llama3_2/text_prompt_format.md
llama_models/llama3_2/vision_prompt_format.md
llama_models/llama4/__init__.py
llama_models/llama4/args.py
llama_models/llama4/chat_format.py
llama_models/llama4/datatypes.py
llama_models/llama4/ffn.py
llama_models/llama4/generation.py
llama_models/llama4/model.py
llama_models/llama4/moe.py
llama_models/llama4/preprocess.py
llama_models/llama4/tokenizer.model
llama_models/llama4/tokenizer.py
llama_models/llama4/quantization/__init__.py
llama_models/llama4/quantization/loader.py
llama_models/llama4/scripts/chat_completion.py
llama_models/llama4/scripts/completion.py
llama_models-0.3.0.dist-info/licenses/LICENSE
llama_models-0.3.0.dist-info/METADATA
llama_models-0.3.0.dist-info/WHEEL
llama_models-0.3.0.dist-info/entry_points.txt
llama_models-0.3.0.dist-info/top_level.txt
llama_models-0.3.0.dist-info/RECORD
