Metadata-Version: 2.4
Name: llama_models
Version: 0.3.0
Summary: Llama models
Author-email: Meta Llama <llama-oss@meta.com>
Project-URL: Homepage, https://github.com/meta-llama/llama-models
Requires-Python: >=3.10
License-File: LICENSE
Requires-Dist: PyYAML
Requires-Dist: jinja2>=3.1.6
Requires-Dist: tiktoken
Requires-Dist: pydantic>=2
Requires-Dist: Pillow
Requires-Dist: rich
Requires-Dist: httpx
Requires-Dist: termcolor
Requires-Dist: huggingface-hub
Provides-Extra: dev
Requires-Dist: pytest; extra == "dev"
Requires-Dist: black; extra == "dev"
Requires-Dist: isort; extra == "dev"
Requires-Dist: mypy; extra == "dev"
Requires-Dist: ruff; extra == "dev"
Provides-Extra: torch
Requires-Dist: torch; extra == "torch"
Requires-Dist: torchvision; extra == "torch"
Requires-Dist: fairscale; extra == "torch"
Requires-Dist: fire; extra == "torch"
Requires-Dist: blobfile; extra == "torch"
Requires-Dist: fbgemm-gpu-genai==1.1.2; extra == "torch"
Dynamic: license-file
